{
    "chin":"cgt_chin_rotation",
    "eyebrow_in_l":"cgt_eyebrow.I.L",
    "eyebrow_in_r":"cgt_eyebrow.I.R",
    "eyebrow_mid_l":"cgt_eyebrow.M.L",
    "eyebrow_mid_r":"cgt_eyebrow.M.R",
    "eyebrow_out_l":"cgt_eyebrow.O.L",
    "eyebrow_out_r":"cgt_eyebrow.O.R",
    "face":"cgt_face_vertex_",
    "head":"cgt_face_rotation",
    "left_eye":"cgt_eye_driver.L",
    "left_eye_b":"cgt_eye_driver.B.L",
    "left_eye_t":"cgt_eye_driver.T.L",
    "left_eyebrow":"cgt_eyebrow_driver.L",
    "mouth":"cgt_mouth_driver",
    "mouth_b":"cgt_mouth_driver.B",
    "mouth_corners":"cgt_mouth_corner_driver",
    "mouth_l":"cgt_mouth_driver.L",
    "mouth_r":"cgt_mouth_driver.R",
    "mouth_t":"cgt_mouth_driver.T",
    "right_eye":"cgt_eye_driver.R",
    "right_eye_b":"cgt_eye_driver.B.R",
    "right_eye_t":"cgt_eye_driver.T.R",
    "right_eyebrow":"cgt_eyebrow_driver.R"
}